cubicweb_pwd_policy/__init__.py
cubicweb_pwd_policy/__pkginfo__.py
cubicweb_pwd_policy/entities.py
cubicweb_pwd_policy/hooks.py
cubicweb_pwd_policy/schema.py
cubicweb_pwd_policy/views.py
cubicweb_pwd_policy/i18n/en.po
cubicweb_pwd_policy/i18n/es.po
cubicweb_pwd_policy/i18n/fr.po
cubicweb_pwd_policy/migration/postcreate.py
cubicweb_pwd_policy-2.0.0.dist-info/METADATA
cubicweb_pwd_policy-2.0.0.dist-info/WHEEL
cubicweb_pwd_policy-2.0.0.dist-info/entry_points.txt
cubicweb_pwd_policy-2.0.0.dist-info/top_level.txt
cubicweb_pwd_policy-2.0.0.dist-info/RECORD
